plover_open_url.py
plover_open_url-0.0.2.dist-info/DESCRIPTION.rst
plover_open_url-0.0.2.dist-info/METADATA
plover_open_url-0.0.2.dist-info/RECORD
plover_open_url-0.0.2.dist-info/WHEEL
plover_open_url-0.0.2.dist-info/entry_points.txt
plover_open_url-0.0.2.dist-info/metadata.json
plover_open_url-0.0.2.dist-info/top_level.txt
plover_open_url-0.0.2.dist-info/zip-safe
