Metadata-Version: 2.0
Name: plover-open-url
Version: 0.0.2
Summary: Command plugin for Plover to open a URL
Home-page: https://github.com/nsmarkop/plover_open_url
Author: Nick Markopoulos
Author-email: nsmarkop@gmail.com
License: MIT
Keywords: plover plover_plugin
Platform: UNKNOWN
Classifier: Development Status :: 4 - Beta
Classifier: Environment :: Plugins
Classifier: Intended Audience :: End Users/Desktop
Classifier: License :: OSI Approved :: MIT License
Classifier: Operating System :: OS Independent
Classifier: Programming Language :: Python :: 3
Classifier: Programming Language :: Python :: 3.6
